{"klaviyo.com":{"/":{"kl_csrftoken":{"key":"kl_csrftoken","value":"SkVtDGns7JmSXxxi9nJxbPDGtmYs1NeI","expires":"2026-07-09T11:34:38.000Z","maxAge":31449600,"domain":"klaviyo.com","path":"/","secure":true,"hostOnly":false,"creation":"2025-07-09T13:38:53.364Z","lastAccessed":"2025-07-10T12:03:24.985Z","sameSite":"none"},"kl_test_cookie":{"key":"kl_test_cookie","value":"test","domain":"klaviyo.com","path":"/","secure":true,"hostOnly":false,"creation":"2025-07-09T13:38:53.364Z","lastAccessed":"2025-07-10T12:03:24.985Z"},"kl_sessionid":{"key":"kl_sessionid","value":"eq6ksb338e4ost6b1vfafghahm3p8as0","expires":"2025-07-16T13:38:50.000Z","maxAge":524125,"domain":"klaviyo.com","path":"/","secure":true,"httpOnly":true,"hostOnly":false,"creation":"2025-07-09T13:38:53.365Z","lastAccessed":"2025-07-10T12:03:25.277Z","sameSite":"none"}}},"www.klaviyo.com":{"/":{"klaviyo_user_device_trusted_cookie":{"key":"klaviyo_user_device_trusted_cookie","value":"\"trWPe6Q7oqIUD8U94+3BbIkaqTldZ4Iml3Ig4FeiOFfzgvKTWVaVgMzuEinS2guLxYtfcWKSYvurJe1CdCuMXAG/Vxm8cOfbc02tIhIqVv1P745a6gsJ884mJ/q5tvq5jjlqvUCSA3abooPJucCmMNkjcP2pKO3Ht1Irls+FbFiqYU67UCXkMnPh\"","domain":"www.klaviyo.com","path":"/","secure":true,"httpOnly":true,"hostOnly":false,"creation":"2025-07-09T13:38:53.364Z","lastAccessed":"2025-07-10T12:03:24.985Z"}}}}